examples/__init__.py
examples/concertbot/__init__.py
examples/concertbot/actions.py
examples/concertbot/train.py
examples/concertbot/train_interactive.py
examples/concertbot/visualize.py
examples/nlg_server/__init__.py
examples/nlg_server/nlg_server.py
examples/restaurantbot/__init__.py
examples/restaurantbot/actions.py
examples/restaurantbot/bot.py
examples/restaurantbot/policy.py
kidx_core/__init__.py
kidx_core/agent.py
kidx_core/broker.py
kidx_core/config.py
kidx_core/constants.py
kidx_core/conversation.py
kidx_core/default_config.yml
kidx_core/dispatcher.py
kidx_core/domain.py
kidx_core/evaluate.py
kidx_core/exceptions.py
kidx_core/featurizers.py
kidx_core/interpreter.py
kidx_core/processor.py
kidx_core/remote.py
kidx_core/restore.py
kidx_core/run.py
kidx_core/server.py
kidx_core/slots.py
kidx_core/tracker_store.py
kidx_core/trackers.py
kidx_core/train.py
kidx_core/utils.py
kidx_core/version.py
kidx_core/visualize.py
kidx_core/actions/__init__.py
kidx_core/actions/action.py
kidx_core/channels/__init__.py
kidx_core/channels/botframework.py
kidx_core/channels/callback.py
kidx_core/channels/channel.py
kidx_core/channels/console.py
kidx_core/channels/facebook.py
kidx_core/channels/kidx_chat.py
kidx_core/channels/mattermost.py
kidx_core/channels/rocketchat.py
kidx_core/channels/slack.py
kidx_core/channels/socketio.py
kidx_core/channels/telegram.py
kidx_core/channels/twilio.py
kidx_core/channels/webexteams.py
kidx_core/cli/__init__.py
kidx_core/cli/arguments.py
kidx_core/events/__init__.py
kidx_core/nlg/__init__.py
kidx_core/nlg/callback.py
kidx_core/nlg/generator.py
kidx_core/nlg/template.py
kidx_core/policies/__init__.py
kidx_core/policies/embedding_policy.py
kidx_core/policies/ensemble.py
kidx_core/policies/fallback.py
kidx_core/policies/form_policy.py
kidx_core/policies/keras_policy.py
kidx_core/policies/memoization.py
kidx_core/policies/policy.py
kidx_core/policies/sklearn_policy.py
kidx_core-0.0.1a4.dist-info/LICENSE.txt
kidx_core-0.0.1a4.dist-info/METADATA
kidx_core-0.0.1a4.dist-info/RECORD
kidx_core-0.0.1a4.dist-info/WHEEL
kidx_core-0.0.1a4.dist-info/top_level.txt
