Metadata-Version: 2.1
Name: kidx-core
Version: 0.0.1a4
Summary: Machine learning based dialogue engine for conversational software.
Home-page: https://rasa.com
Author: Kidx AI Technologies Education
Author-email: nlp@mykidx.com
Maintainer: Colin Gao
Maintainer-email: colin.gao@mykidx.com
License: Apache 2.0
Download-URL: http://git.mykidx.com/nlp/kidx_core/-/archive/0.0.1a4/kidx_core-0.0.1a4.tar.gz
Project-URL: Bug Reports, http://redmine.mykidx.com/projects/kidx-nlu/issues
Project-URL: Source, http://git.mykidx.com/nlp/kidx_core
Keywords: nlp machine-learning machine-learning-library bot bots botkit kidx conversational-agents conversational-ai chatbotchatbot-framework bot-framework
Platform: UNKNOWN
Classifier: Development Status :: 4 - Beta
Classifier: Intended Audience :: Developers
Classifier: License :: OSI Approved :: Apache Software License
Classifier: Programming Language :: Python
Classifier: Programming Language :: Python :: 3.5
Classifier: Programming Language :: Python :: 3.6
Classifier: Topic :: Software Development :: Libraries
Provides-Extra: test
Requires-Dist: jsonpickle (~=1.0)
Requires-Dist: redis (~=2.0)
Requires-Dist: fakeredis (~=0.10.0)
Requires-Dist: pymongo (~=3.7)
Requires-Dist: numpy (~=1.16)
Requires-Dist: scipy (~=1.2)
Requires-Dist: typing (~=3.0)
Requires-Dist: requests (~=2.20)
Requires-Dist: tensorflow (~=1.12.0)
Requires-Dist: apscheduler (~=3.0)
Requires-Dist: tqdm (~=4.0)
Requires-Dist: networkx (~=2.2)
Requires-Dist: fbmessenger (~=5.0)
Requires-Dist: pykwalify (~=1.7.0)
Requires-Dist: coloredlogs (~=10.0)
Requires-Dist: ruamel.yaml (~=0.15.0)
Requires-Dist: scikit-learn (~=0.20.0)
Requires-Dist: slackclient (~=1.0)
Requires-Dist: python-telegram-bot (~=11.0)
Requires-Dist: twilio (~=6.0)
Requires-Dist: webexteamssdk (~=1.0)
Requires-Dist: mattermostwrapper (~=2.0)
Requires-Dist: rocketchat-API (~=0.6.0)
Requires-Dist: colorhash (~=1.0)
Requires-Dist: pika (~=0.12.0)
Requires-Dist: jsonschema (~=2.6)
Requires-Dist: packaging (~=18.0)
Requires-Dist: gevent (~=1.4)
Requires-Dist: pytz (~=2018.9)
Requires-Dist: python-dateutil (~=2.7)
Requires-Dist: kidx-nlu (~=0.0.1a6)
Requires-Dist: kidx-core-sdk (~=0.0.1a2)
Requires-Dist: colorclass (~=2.2)
Requires-Dist: terminaltables (~=3.1)
Requires-Dist: questionary (>=1.0.1)
Requires-Dist: sanic (~=0.8.0)
Requires-Dist: sanic-cors (~=0.9.0)
Requires-Dist: sanic-jwt (~=1.2)
Requires-Dist: aiohttp (~=3.3)
Requires-Dist: python-socketio (~=3.0)
Requires-Dist: pydot (~=1.4)
Requires-Dist: keras-applications (==1.0.6)
Requires-Dist: keras-preprocessing (==1.0.5)
Provides-Extra: test
Requires-Dist: pytest (~=3.0); extra == 'test'
Requires-Dist: pytest-pycodestyle (~=1.3); extra == 'test'
Requires-Dist: pytest-cov (~=2.0); extra == 'test'
Requires-Dist: pytest-localserver (~=0.4.0); extra == 'test'
Requires-Dist: pytest-asyncio (~=0.9.0); extra == 'test'
Requires-Dist: treq (~=17.0); extra == 'test'
Requires-Dist: freezegun (~=0.3.0); extra == 'test'
Requires-Dist: nbsphinx (>=0.3); extra == 'test'
Requires-Dist: matplotlib (~=2.0); extra == 'test'
Requires-Dist: responses (~=0.9.0); extra == 'test'
Requires-Dist: httpretty (~=0.9.0); extra == 'test'
